salesforce_connector/__init__.py
salesforce_connector/config.py
salesforce_connector/connector.py
salesforce_connector/cache/__init__.py
salesforce_connector/cache/field_cache.py
salesforce_connector/operations/__init__.py
salesforce_connector/operations/bulk_v2.py
salesforce_connector/operations/extract.py
salesforce_connector/operations/load.py
salesforce_connector/types/__init__.py
salesforce_connector/types/field_types.py
salesforce_connector/utils/__init__.py
salesforce_connector/utils/glue_utils.py
salesforce_connector/utils/logging_utils.py
salesforce_connector/utils/query_utils.py
salesforce_connector/utils/secrets_utils.py
salesforce_connector/utils/spark_utils.py
salesforce_connector/utils/token_manager.py
salesforce_spark_connector-0.1.0.dist-info/LICENSE
salesforce_spark_connector-0.1.0.dist-info/METADATA
salesforce_spark_connector-0.1.0.dist-info/WHEEL
salesforce_spark_connector-0.1.0.dist-info/top_level.txt
salesforce_spark_connector-0.1.0.dist-info/RECORD
