Metadata-Version: 2.2
Name: salesforce-spark-connector
Version: 0.1.0
Summary: A scalable Python connector for Salesforce with multiple data processing engines
Home-page: https://github.com/timmapuramreddy/salesforce-spark-connector
Author: T Mohan Reddy
Author-email: timmapuramreddy@gmail.com
Classifier: Development Status :: 4 - Beta
Classifier: Intended Audience :: Developers
Classifier: License :: OSI Approved :: MIT License
Classifier: Operating System :: OS Independent
Classifier: Programming Language :: Python :: 3
Classifier: Programming Language :: Python :: 3.8
Classifier: Programming Language :: Python :: 3.9
Classifier: Programming Language :: Python :: 3.10
Classifier: Topic :: Database
Classifier: Topic :: Software Development :: Libraries :: Python Modules
Requires-Python: >=3.8
License-File: LICENSE
Requires-Dist: requests>=2.25.0
Requires-Dist: simple-salesforce>=1.12.4
Requires-Dist: requests-oauthlib>=1.3.1
Requires-Dist: python-dotenv>=0.19.0
Requires-Dist: pandas>=1.3.0
Requires-Dist: pyarrow>=14.0.1
Provides-Extra: spark
Requires-Dist: pyspark>=3.0.0; extra == "spark"
Provides-Extra: duckdb
Requires-Dist: duckdb>=0.9.0; extra == "duckdb"
Provides-Extra: dev
Requires-Dist: pytest>=6.0.0; extra == "dev"
Requires-Dist: pytest-cov>=2.0.0; extra == "dev"
Requires-Dist: flake8>=3.9.0; extra == "dev"
Requires-Dist: black>=21.0; extra == "dev"
Requires-Dist: mypy>=0.900; extra == "dev"
Requires-Dist: twine>=3.4.0; extra == "dev"
Requires-Dist: build>=0.7.0; extra == "dev"
Dynamic: author
Dynamic: author-email
Dynamic: classifier
Dynamic: description
Dynamic: description-content-type
Dynamic: home-page
Dynamic: provides-extra
Dynamic: requires-dist
Dynamic: requires-python
Dynamic: summary
